zhttp/__init__.py
zhttp-0.1.dist-info/WHEEL
zhttp-0.1.dist-info/METADATA
zhttp-0.1.dist-info/DESCRIPTION.rst
zhttp-0.1.dist-info/RECORD
zhttp-0.1.dist-info/metadata.json
zhttp-0.1.dist-info/top_level.txt
