Metadata-Version: 2.0
Name: zhttp
Version: 0.1
Summary: zouhuigang zhttp package 
Home-page: http://github.com/zouhuigang
Author: zouhuigang
Author-email: zouhuigang888@gmail.com
License: MIT
Platform: UNKNOWN
